psychometrics/BestPEST.py
psychometrics/Hybrid.py
psychometrics/PEST.py
psychometrics/__init__.py
psychometrics-0.1.2.dist-info/LICENSE.txt
psychometrics-0.1.2.dist-info/METADATA
psychometrics-0.1.2.dist-info/WHEEL
psychometrics-0.1.2.dist-info/top_level.txt
psychometrics-0.1.2.dist-info/RECORD
