Metadata-Version: 2.1
Name: psychometrics
Version: 0.1.2
Summary: psychometrics is a library for psychological measurement experiment
Home-page: https://github.com/tetsuzawa/psychometrics
Author: Tetsu Takizawa
Author-email: tetsu.varmos@gmail.com
License: UNKNOWN
Platform: UNKNOWN
Requires-Dist: numpy
Requires-Dist: matplotlib
